LICENSE
MANIFEST.in
README.md
setup.py
mping/__init__.py
mping/mping.py
mping.egg-info/PKG-INFO
mping.egg-info/SOURCES.txt
mping.egg-info/dependency_links.txt
mping.egg-info/entry_points.txt
mping.egg-info/top_level.txt