Metadata-Version: 1.1
Name: mping
Version: 0.1.1
Summary: Ping multiple hosts concurrently and find the fastest to you.
Home-page: https://github.com/youfou/mping
Author: Youfou
Author-email: youfou@qq.com
License: Apache 2.0
Keywords: ping,host,monitor
Platform: UNKNOWN
Classifier: Development Status :: 4 - Beta
Classifier: License :: OSI Approved :: Apache Software License
Classifier: Programming Language :: Python :: 3
Classifier: Operating System :: OS Independent
Classifier: Intended Audience :: System Administrators
Classifier: Topic :: System :: Networking :: Monitoring
Classifier: Topic :: Utilities
